swimmable/__init__.py
swimmable/client.py
swimmable/exceptions.py
swimmable/types.py
swimmable/utils.py
swimmable_sdk-1.0.0.dist-info/licenses/LICENSE
swimmable_sdk-1.0.0.dist-info/METADATA
swimmable_sdk-1.0.0.dist-info/WHEEL
swimmable_sdk-1.0.0.dist-info/top_level.txt
swimmable_sdk-1.0.0.dist-info/RECORD
